lccommon/__init__.py
lccommon/net_util.py
lccommon/spice_parser.py
librecell_common-0.0.3.dist-info/LICENSE
librecell_common-0.0.3.dist-info/METADATA
librecell_common-0.0.3.dist-info/WHEEL
librecell_common-0.0.3.dist-info/top_level.txt
librecell_common-0.0.3.dist-info/RECORD
